ae/shell.py
ae_shell-0.3.12.dist-info/licenses/LICENSE.md
ae_shell-0.3.12.dist-info/METADATA
ae_shell-0.3.12.dist-info/WHEEL
ae_shell-0.3.12.dist-info/top_level.txt
ae_shell-0.3.12.dist-info/zip-safe
ae_shell-0.3.12.dist-info/RECORD
